{"node_dict": {"37124": {"node_name": null, "node_label": "32", "insns": [[37124, "push", "{r4, r5, r6, r7, r8, sb, sl, fp, lr}"], [37128, "cmp", "r0, #1"], [37132, "ldr", "r4, [pc, #0x1d0]"], [37136, "sub", "sp, sp, #0x24"], [37140, "mov", "sl, r0"], [37144, "str", "r1, [sp, #8]"], [37148, "add", "r4, pc, r4"], [37152, "beq", "#0x917c"]]}, "37244": {"node_name": null, "node_label": "4", "insns": [[37244, "bl", "#0x9070"]]}, "37156": {"node_name": null, "node_label": "88", "insns": [[37156, "ldr", "r3, [pc, #0x1bc]"], [37160, "mov", "r5, #0"], [37164, "mov", "r7, r5"], [37168, "mov", "fp, r5"], [37172, "mov", "sb, r5"], [37176, "mov", "r6, r5"], [37180, "add", "r3, r4, r3"], [37184, "mov", "r8, r5"], [37188, "str", "r3, [sp, #0xc]"], [37192, "ldr", "r3, [pc, #0x19c]"], [37196, "add", "r3, r4, r3"], [37200, "str", "r3, [sp, #0x10]"], [37204, "ldr", "r3, [pc, #0x194]"], [37208, "add", "r3, r4, r3"], [37212, "str", "r3, [sp, #0x14]"], [37216, "ldr", "r3, [pc, #0x18c]"], [37220, "add", "r3, r4, r3"], [37224, "str", "r3, [sp, #0x18]"], [37228, "ldr", "r3, [pc, #0x184]"], [37232, "add", "r3, r4, r3"], [37236, "str", "r3, [sp, #0x1c]"], [37240, "b", "#0x92a8"]]}, "36976": {"node_name": null, "node_label": "24", "insns": [[36976, "push", "{r4, lr}"], [36980, "ldr", "r4, [pc, #0x64]"], [36984, "ldr", "r0, [pc, #0x64]"], [36988, "add", "r4, pc, r4"], [36992, "add", "r0, r4, r0"], [36996, "bl", "#0x8f54"]]}, "37248": {"node_name": null, "node_label": "8", "insns": [[37248, "mov", "r0, #0"], [37252, "b", "#0x92dc"]]}, "37544": {"node_name": null, "node_label": "16", "insns": [[37544, "mov", "r0, sl"], [37548, "ldr", "r1, [sp, #8]"], [37552, "ldr", "r2, [sp, #0xc]"], [37556, "bl", "#0x8f18"]]}, "37596": {"node_name": null, "node_label": "8", "insns": [[37596, "add", "sp, sp, #0x24"], [37600, "pop", "{r4, r5, r6, r7, r8, sb, sl, fp, pc}"]]}, "36632": {"node_name": null, "node_label": "12", "insns": [[36632, "add", "ip, pc, #0, #12"], [36636, "add", "ip, ip, #0xb000"], [36640, "ldr", "pc, [ip, #0xe34]!"]]}, "37560": {"node_name": null, "node_label": "8", "insns": [[37560, "cmn", "r0, #1"], [37564, "bne", "#0x9188"]]}, "37256": {"node_name": null, "node_label": "8", "insns": [[37256, "cmp", "r0, #0x67"], [37260, "beq", "#0x9200"]]}, "37568": {"node_name": null, "node_label": "28", "insns": [[37568, "mov", "r0, r8"], [37572, "mov", "r1, r6"], [37576, "mov", "r2, sb"], [37580, "mov", "r3, fp"], [37584, "str", "r7, [sp]"], [37588, "str", "r5, [sp, #4]"], [37592, "bl", "#0x9348"]]}, "37376": {"node_name": null, "node_label": "8", "insns": [[37376, "ldr", "r6, [sp, #0x10]"], [37380, "b", "#0x92a8"]]}, "37264": {"node_name": null, "node_label": "4", "insns": [[37264, "bgt", "#0x91c8"]]}, "37704": {"node_name": null, "node_label": "52", "insns": [[37704, "push", "{r4, r5, r6, r7, r8, sb, sl, fp, lr}"], [37708, "mov", "r8, r0"], [37712, "ldr", "r6, [pc, #0xf2c]"], [37716, "sub", "sp, sp, #0x510"], [37720, "sub", "sp, sp, #0xc"], [37724, "mov", "r4, r1"], [37728, "ldr", "r0, [pc, #0xf20]"], [37732, "mov", "r5, r2"], [37736, "add", "r6, pc, r6"], [37740, "mov", "sl, r3"], [37744, "ldr", "sb, [sp, #0x540]"], [37748, "add", "r0, r6, r0"], [37752, "bl", "#0x8da4"]]}, "37320": {"node_name": null, "node_label": "12", "insns": [[37320, "cmp", "r0, #0x72"], [37324, "ldreq", "r6, [sp, #0x14]"], [37328, "beq", "#0x92a8"]]}, "37268": {"node_name": null, "node_label": "8", "insns": [[37268, "cmp", "r0, #0x62"], [37272, "beq", "#0x924c"]]}, "37332": {"node_name": null, "node_label": "4", "insns": [[37332, "bgt", "#0x91ec"]]}, "37452": {"node_name": null, "node_label": "16", "insns": [[37452, "ldr", "r3, [pc, #0xa8]"], [37456, "ldr", "r3, [r4, r3]"], [37460, "ldr", "r7, [r3]"], [37464, "b", "#0x92a8"]]}, "37276": {"node_name": null, "node_label": "4", "insns": [[37276, "bgt", "#0x91b4"]]}, "37356": {"node_name": null, "node_label": "8", "insns": [[37356, "cmp", "r0, #0x73"], [37360, "beq", "#0x9208"]]}, "37336": {"node_name": null, "node_label": "8", "insns": [[37336, "cmp", "r0, #0x68"], [37340, "beq", "#0x9298"]]}, "37300": {"node_name": null, "node_label": "8", "insns": [[37300, "cmp", "r0, #0x64"], [37304, "beq", "#0x925c"]]}, "37280": {"node_name": null, "node_label": "8", "insns": [[37280, "cmp", "r0, #0x3f"], [37284, "beq", "#0x9270"]]}, "37384": {"node_name": null, "node_label": "16", "insns": [[37384, "ldr", "r3, [pc, #0xec]"], [37388, "ldr", "r3, [r4, r3]"], [37392, "ldr", "r8, [r3]"], [37396, "b", "#0x92a8"]]}, "37364": {"node_name": null, "node_label": "8", "insns": [[37364, "cmp", "r0, #0x74"], [37368, "bne", "#0x9298"]]}, "37528": {"node_name": null, "node_label": "4", "insns": [[37528, "bl", "#0x9070"]]}, "37344": {"node_name": null, "node_label": "8", "insns": [[37344, "cmp", "r0, #0x70"], [37348, "bne", "#0x9298"]]}, "37468": {"node_name": null, "node_label": "20", "insns": [[37468, "ldr", "r3, [pc, #0x98]"], [37472, "ldr", "r6, [sp, #0x1c]"], [37476, "ldr", "r3, [r4, r3]"], [37480, "ldr", "r7, [r3]"], [37484, "b", "#0x92a8"]]}, "37308": {"node_name": null, "node_label": "8", "insns": [[37308, "cmp", "r0, #0x65"], [37312, "bne", "#0x9298"]]}, "37488": {"node_name": null, "node_label": "32", "insns": [[37488, "ldr", "r3, [pc, #0x88]"], [37492, "ldr", "r0, [pc, #0x88]"], [37496, "ldr", "r1, [pc, #0x88]"], [37500, "ldr", "r3, [r4, r3]"], [37504, "add", "r0, r4, r0"], [37508, "add", "r1, r4, r1"], [37512, "ldr", "r2, [r3]"], [37516, "bl", "#0x8f48"]]}, "37288": {"node_name": null, "node_label": "8", "insns": [[37288, "cmp", "r0, #0x61"], [37292, "bne", "#0x9298"]]}, "37372": {"node_name": null, "node_label": "4", "insns": [[37372, "b", "#0x9218"]]}, "37532": {"node_name": null, "node_label": "4", "insns": [[37532, "b", "#0x92a8"]]}, "37352": {"node_name": null, "node_label": "4", "insns": [[37352, "b", "#0x922c"]]}, "37316": {"node_name": null, "node_label": "4", "insns": [[37316, "b", "#0x92a0"]]}, "36680": {"node_name": null, "node_label": "12", "insns": [[36680, "add", "ip, pc, #0, #12"], [36684, "add", "ip, ip, #0xb000"], [36688, "ldr", "pc, [ip, #0xe14]!"]]}, "37520": {"node_name": null, "node_label": "8", "insns": [[37520, "mvn", "r0, #0"], [37524, "b", "#0x92dc"]]}, "37296": {"node_name": null, "node_label": "4", "insns": [[37296, "b", "#0x923c"]]}, "37400": {"node_name": null, "node_label": "20", "insns": [[37400, "ldr", "r3, [pc, #0xdc]"], [37404, "ldr", "r6, [sp, #0x18]"], [37408, "ldr", "r3, [r4, r3]"], [37412, "ldr", "r5, [r3]"], [37416, "b", "#0x92a8"]]}, "37420": {"node_name": null, "node_label": "16", "insns": [[37420, "ldr", "r3, [pc, #0xc8]"], [37424, "ldr", "r3, [r4, r3]"], [37428, "ldr", "sb, [r3]"], [37432, "b", "#0x92a8"]]}, "37536": {"node_name": null, "node_label": "8", "insns": [[37536, "ldr", "r6, [pc, #0x64]"], [37540, "add", "r6, r4, r6"]]}, "37436": {"node_name": null, "node_label": "16", "insns": [[37436, "ldr", "r3, [pc, #0xb8]"], [37440, "ldr", "r3, [r4, r3]"], [37444, "ldr", "fp, [r3]"], [37448, "b", "#0x92a8"]]}}, "edge_list": [[37124, 37244], [37124, 37156], [37244, 36976], [37244, 37248], [37156, 37544], [37248, 37596], [37544, 36632], [37544, 37560], [37560, 37256], [37560, 37568], [37256, 37376], [37256, 37264], [37568, 37704], [37568, 37596], [37376, 37544], [37264, 37320], [37264, 37268], [37320, 37544], [37320, 37332], [37268, 37452], [37268, 37276], [37332, 37356], [37332, 37336], [37452, 37544], [37276, 37300], [37276, 37280], [37356, 37384], [37356, 37364], [37336, 37528], [37336, 37344], [37300, 37468], [37300, 37308], [37280, 37488], [37280, 37288], [37384, 37544], [37364, 37528], [37364, 37372], [37528, 36976], [37528, 37532], [37344, 37528], [37344, 37352], [37468, 37544], [37308, 37528], [37308, 37316], [37488, 36680], [37488, 37520], [37288, 37528], [37288, 37296], [37372, 37400], [37532, 37544], [37352, 37420], [37316, 37536], [37520, 37596], [37296, 37436], [37400, 37544], [37420, 37544], [37536, 37544], [37436, 37544]], "label": "benign", "startpoint": 37124, "endpoints": [37596]}