{"node_dict": {"38112": {"node_name": null, "node_label": "84", "insns": [[38112, "push", "{r4, r5, r6, r7, r8, sb, sl, fp, lr}"], [38116, "mov", "r8, #0"], [38120, "ldr", "r7, [pc, #0x2a0]"], [38124, "cmp", "r0, #1"], [38128, "sub", "sp, sp, #0x14"], [38132, "mov", "r5, r1"], [38136, "ldr", "sl, [pc, #0x294]"], [38140, "mov", "r6, r0"], [38144, "mov", "r3, r7"], [38148, "strb", "r8, [sl]"], [38152, "ldr", "r2, [r1]"], [38156, "str", "r8, [r3], #0xc"], [38160, "str", "r8, [r3]"], [38164, "add", "r3, r7, #0x10"], [38168, "str", "r8, [r3]"], [38172, "movw", "r3, #0x1450"], [38176, "str", "r3, [r7, #8]"], [38180, "ldr", "r3, [pc, #0x26c]"], [38184, "str", "r2, [sl, #4]"], [38188, "str", "r3, [r7, #4]"], [38192, "ble", "#0x96f4"]]}, "38644": {"node_name": null, "node_label": "8", "insns": [[38644, "ldr", "r0, [pc, #0xc0]"], [38648, "bl", "#0x8a68"]]}, "38196": {"node_name": null, "node_label": "24", "insns": [[38196, "mov", "r4, #1"], [38200, "mov", "r0, #2"], [38204, "mov", "fp, r4"], [38208, "ldr", "r1, [pc, #0x254]"], [38212, "mov", "r2, r6"], [38216, "bl", "#0x8d44"]]}, "35432": {"node_name": null, "node_label": "12", "insns": [[35432, "add", "ip, pc, #0, #12"], [35436, "add", "ip, ip, #0xa000"], [35440, "ldr", "pc, [ip, #0xce8]!"]]}, "38652": {"node_name": null, "node_label": "12", "insns": [[38652, "movw", "r1, #0x1450"], [38656, "ldr", "r0, [pc, #0xb8]"], [38660, "bl", "#0x8a2c"]]}, "36164": {"node_name": null, "node_label": "28", "insns": [[36164, "push", "{r1, r2, r3}"], [36168, "ldr", "r3, [pc, #0x4c]"], [36172, "str", "lr, [sp, #-4]!"], [36176, "sub", "sp, sp, #8"], [36180, "ldrb", "r3, [r3]"], [36184, "cmp", "r3, r0"], [36188, "blt", "#0x8d8c"]]}, "38220": {"node_name": null, "node_label": "4", "insns": [[38220, "str", "r8, [sp]"]]}, "35372": {"node_name": null, "node_label": "12", "insns": [[35372, "add", "ip, pc, #0, #12"], [35376, "add", "ip, ip, #0xa000"], [35380, "ldr", "pc, [ip, #0xd10]!"]]}, "38664": {"node_name": null, "node_label": "8", "insns": [[38664, "ldr", "r0, [pc, #0xb4]"], [38668, "bl", "#0x8a68"]]}, "38224": {"node_name": null, "node_label": "20", "insns": [[38224, "ldr", "r3, [r5, r4, lsl #2]"], [38228, "lsl", "r8, r4, #2"], [38232, "ldrb", "r2, [r3]"], [38236, "cmp", "r2, #0x2d"], [38240, "bne", "#0x960c"]]}, "38672": {"node_name": null, "node_label": "4", "insns": [[38672, "mov", "r0, #1"]]}, "38412": {"node_name": null, "node_label": "12", "insns": [[38412, "ldr", "r2, [sp]"], [38416, "cmp", "r2, #0"], [38420, "bne", "#0x9734"]]}, "38244": {"node_name": null, "node_label": "16", "insns": [[38244, "ldrb", "r1, [r3, #1]"], [38248, "sub", "r2, r1, #0x61"], [38252, "cmp", "r2, #0x15"], [38256, "ldrls", "pc, [pc, r2, lsl #2]"]]}, "38676": {"node_name": null, "node_label": "8", "insns": [[38676, "add", "sp, sp, #0x14"], [38680, "pop", "{r4, r5, r6, r7, r8, sb, sl, fp, pc}"]]}, "38708": {"node_name": null, "node_label": "8", "insns": [[38708, "mov", "r0, #0"], [38712, "b", "#0x9714"]]}, "38424": {"node_name": null, "node_label": "12", "insns": [[38424, "cmp", "r6, r4"], [38428, "ldrlt", "r0, [sp]"], [38432, "blt", "#0x9714"]]}, "38260": {"node_name": null, "node_label": "4", "insns": [[38260, "b", "#0x96e8"]]}, "38496": {"node_name": null, "node_label": "12", "insns": [[38496, "strb", "fp, [r7, #0xc]"], [38500, "add", "r4, r4, #1"], [38504, "b", "#0x9604"]]}, "38632": {"node_name": null, "node_label": "12", "insns": [[38632, "ldr", "r0, [pc, #0xc8]"], [38636, "mov", "r1, r3"], [38640, "bl", "#0x8d04"]]}, "38540": {"node_name": null, "node_label": "12", "insns": [[38540, "add", "sb, r4, #1"], [38544, "cmp", "r6, sb"], [38548, "ble", "#0x96f4"]]}, "38508": {"node_name": null, "node_label": "12", "insns": [[38508, "strb", "fp, [sl]"], [38512, "add", "r4, r4, #1"], [38516, "b", "#0x9604"]]}, "38352": {"node_name": null, "node_label": "28", "insns": [[38352, "ldr", "r0, [pc, #0x1c8]"], [38356, "mov", "ip, #1"], [38360, "ldr", "r1, [pc, #0x1c4]"], [38364, "ldr", "r2, [pc, #0x1c4]"], [38368, "ldr", "r3, [pc, #0x1c4]"], [38372, "str", "ip, [sp]"], [38376, "bl", "#0x8d04"]]}, "38520": {"node_name": null, "node_label": "20", "insns": [[38520, "add", "r3, r4, #1"], [38524, "add", "r4, r4, #2"], [38528, "ldr", "r3, [r5, r3, lsl #2]"], [38532, "str", "r3, [r7, #0x10]"], [38536, "b", "#0x9604"]]}, "38436": {"node_name": null, "node_label": "12", "insns": [[38436, "rsb", "r0, r4, r6"], [38440, "add", "r1, r5, r4, lsl #2"], [38444, "bl", "#0x9e80"]]}, "38404": {"node_name": null, "node_label": "8", "insns": [[38404, "cmp", "r6, r4"], [38408, "bgt", "#0x9550"]]}, "36100": {"node_name": null, "node_label": "32", "insns": [[36100, "push", "{r0, r1, r2, r3}"], [36104, "str", "lr, [sp, #-4]!"], [36108, "sub", "sp, sp, #0xc"], [36112, "add", "r3, sp, #0x14"], [36116, "mov", "r1, r3"], [36120, "ldr", "r0, [sp, #0x10]"], [36124, "str", "r3, [sp, #4]"], [36128, "bl", "#0x8b10"]]}, "38552": {"node_name": null, "node_label": "8", "insns": [[38552, "cmp", "r1, #0x61"], [38556, "beq", "#0x971c"]]}, "38380": {"node_name": null, "node_label": "24", "insns": [[38380, "mov", "r2, r4"], [38384, "mov", "r0, #2"], [38388, "ldr", "r1, [pc, #0x1b4]"], [38392, "add", "r4, r4, #1"], [38396, "ldr", "r3, [r5, r8]"], [38400, "bl", "#0x8d44"]]}, "40576": {"node_name": null, "node_label": "24", "insns": [[40576, "push", "{r4, r5, r6, r7, r8, sb, sl, fp, lr}"], [40580, "subs", "sb, r0, #0"], [40584, "sub", "sp, sp, #0xc"], [40588, "movle", "r3, #0"], [40592, "strle", "r3, [sp, #4]"], [40596, "bgt", "#0x9ea4"]]}, "38448": {"node_name": null, "node_label": "8", "insns": [[38448, "subs", "r4, r0, #0"], [38452, "beq", "#0x9784"]]}, "38684": {"node_name": null, "node_label": "24", "insns": [[38684, "ldr", "r3, [r5, sb, lsl #2]"], [38688, "add", "r2, r5, sb, lsl #2"], [38692, "str", "r2, [sp, #4]"], [38696, "str", "r3, [r7, #4]"], [38700, "ldr", "r3, [r5, r8]"], [38704, "b", "#0x96b8"]]}, "38560": {"node_name": null, "node_label": "8", "insns": [[38560, "cmp", "r1, #0x64"], [38564, "beq", "#0x973c"]]}, "38788": {"node_name": null, "node_label": "4", "insns": [[38788, "bl", "#0x8dc8"]]}, "38456": {"node_name": null, "node_label": "16", "insns": [[38456, "ldr", "r1, [pc, #0x174]"], [38460, "mov", "r2, r4"], [38464, "mov", "r0, #2"], [38468, "bl", "#0x8d44"]]}, "38584": {"node_name": null, "node_label": "20", "insns": [[38584, "mov", "r2, r4"], [38588, "mov", "r0, #2"], [38592, "ldr", "r1, [pc, #0xe8]"], [38596, "add", "r4, r4, #2"], [38600, "bl", "#0x8d44"]]}, "38716": {"node_name": null, "node_label": "24", "insns": [[38716, "add", "r3, r5, sb, lsl #2"], [38720, "ldr", "r0, [r5, sb, lsl #2]"], [38724, "add", "r1, sp, #0xc"], [38728, "mov", "r2, #0xa"], [38732, "str", "r3, [sp, #4]"], [38736, "bl", "#0x8ad4"]]}, "38568": {"node_name": null, "node_label": "16", "insns": [[38568, "cmp", "r1, #0x70"], [38572, "addne", "ip, r5, sb, lsl #2"], [38576, "strne", "ip, [sp, #4]"], [38580, "beq", "#0x9760"]]}, "36296": {"node_name": null, "node_label": "28", "insns": [[36296, "push", "{r4, r5, r6, r7, r8, sb, sl, fp, lr}"], [36300, "sub", "sp, sp, #0xc40"], [36304, "sub", "sp, sp, #4"], [36308, "mov", "r4, #0"], [36312, "str", "r0, [sp, #0x14]"], [36316, "str", "r4, [sp, #0xc3c]"], [36320, "bl", "#0x99f8"]]}, "38792": {"node_name": null, "node_label": "8", "insns": [[38792, "ldr", "r0, [sp]"], [38796, "b", "#0x9714"]]}, "38472": {"node_name": null, "node_label": "8", "insns": [[38472, "mov", "r0, r4"], [38476, "bl", "#0x8dc8"]]}, "38604": {"node_name": null, "node_label": "24", "insns": [[38604, "ldr", "ip, [sp, #4]"], [38608, "mov", "r0, #2"], [38612, "ldr", "r1, [pc, #0xd4]"], [38616, "mov", "r2, sb"], [38620, "ldr", "r3, [ip]"], [38624, "bl", "#0x8d44"]]}, "35540": {"node_name": null, "node_label": "12", "insns": [[35540, "add", "ip, pc, #0, #12"], [35544, "add", "ip, ip, #0xa000"], [35548, "ldr", "pc, [ip, #0xca0]!"]]}, "38740": {"node_name": null, "node_label": "12", "insns": [[38740, "strb", "r0, [r7]"], [38744, "ldr", "r3, [r5, r8]"], [38748, "b", "#0x96b8"]]}, "38752": {"node_name": null, "node_label": "24", "insns": [[38752, "add", "r3, r5, sb, lsl #2"], [38756, "ldr", "r0, [r5, sb, lsl #2]"], [38760, "add", "r1, sp, #0xc"], [38764, "mov", "r2, #0xa"], [38768, "str", "r3, [sp, #4]"], [38772, "bl", "#0x8ad4"]]}, "38480": {"node_name": null, "node_label": "8", "insns": [[38480, "mov", "r0, r4"], [38484, "bl", "#0x8c24"]]}, "38628": {"node_name": null, "node_label": "4", "insns": [[38628, "b", "#0x9604"]]}, "38776": {"node_name": null, "node_label": "12", "insns": [[38776, "str", "r0, [r7, #8]"], [38780, "ldr", "r3, [r5, r8]"], [38784, "b", "#0x96b8"]]}, "35876": {"node_name": null, "node_label": "12", "insns": [[35876, "add", "ip, pc, #0, #12"], [35880, "add", "ip, ip, #0xa000"], [35884, "ldr", "pc, [ip, #0xbc0]!"]]}, "38488": {"node_name": null, "node_label": "8", "insns": [[38488, "ldr", "r0, [sp]"], [38492, "b", "#0x9714"]]}}, "edge_list": [[38112, 38644], [38112, 38196], [38644, 35432], [38644, 38652], [38196, 36164], [38196, 38220], [38652, 35372], [38652, 38664], [38220, 38224], [38664, 35432], [38664, 38672], [38224, 38412], [38224, 38244], [38672, 38676], [38412, 38708], [38412, 38424], [38244, 38260], [38244, 38496], [38244, 38632], [38244, 38540], [38244, 38508], [38244, 38352], [38244, 38520], [38708, 38676], [38424, 38676], [38424, 38436], [38260, 38632], [38496, 38404], [38632, 36100], [38632, 38644], [38540, 38644], [38540, 38552], [38508, 38404], [38352, 36100], [38352, 38380], [38520, 38404], [38436, 40576], [38436, 38448], [38404, 38224], [38404, 38412], [38552, 38684], [38552, 38560], [38380, 36164], [38380, 38404], [38448, 38788], [38448, 38456], [38684, 38584], [38560, 38716], [38560, 38568], [38788, 36296], [38788, 38792], [38456, 36164], [38456, 38472], [38584, 36164], [38584, 38604], [38716, 35540], [38716, 38740], [38568, 38752], [38568, 38584], [38792, 38676], [38472, 36296], [38472, 38480], [38604, 36164], [38604, 38628], [38740, 38584], [38752, 35540], [38752, 38776], [38480, 35876], [38480, 38488], [38628, 38404], [38776, 38584], [38488, 38676]], "label": "benign", "startpoint": 38112, "endpoints": [38676]}